CHANGES.rst
CONTRIBUTORS.rst
DEVELOP.rst
LICENSE.GPL
LICENSE.rst
MANIFEST.in
README.rst
constraints.txt
requirements.txt
setup.cfg
setup.py
docs/conf.py
docs/index.rst
docs/relationinfo.png
src/collective/__init__.py
src/collective.relationhelpers.egg-info/PKG-INFO
src/collective.relationhelpers.egg-info/SOURCES.txt
src/collective.relationhelpers.egg-info/dependency_links.txt
src/collective.relationhelpers.egg-info/entry_points.txt
src/collective.relationhelpers.egg-info/namespace_packages.txt
src/collective.relationhelpers.egg-info/not-zip-safe
src/collective.relationhelpers.egg-info/requires.txt
src/collective.relationhelpers.egg-info/top_level.txt
src/collective/relationhelpers/__init__.py
src/collective/relationhelpers/api.py
src/collective/relationhelpers/configure.zcml
src/collective/relationhelpers/relations_inspect.pt
src/collective/relationhelpers/relations_rebuild.pt
src/collective/relationhelpers/testing.py
src/collective/relationhelpers/tests/__init__.py
src/collective/relationhelpers/tests/test_relations.py