Metadata-Version: 2.1
Name: collective.relationhelpers
Version: 1.3
Summary: Helpers to manage, create, export and rebuild relations in Plone
Home-page: https://github.com/collective/collective.relationhelpers
Author: Philip Bauer
Author-email: bauer@starzel.de
License: GPL version 2
Project-URL: PyPI, https://pypi.python.org/pypi/collective.relationhelpers
Project-URL: Source, https://github.com/collective/collective.relationhelpers
Project-URL: Tracker, https://github.com/collective/collective.relationhelpers/issues
Keywords: Python Plone
Platform: UNKNOWN
Classifier: Environment :: Web Environment
Classifier: Framework :: Plone
Classifier: Framework :: Plone :: Addon
Classifier: Framework :: Plone :: 5.2
Classifier: Programming Language :: Python
Classifier: Programming Language :: Python :: 2.7
Classifier: Programming Language :: Python :: 3.6
Classifier: Programming Language :: Python :: 3.7
Classifier: Programming Language :: Python :: 3.8
Classifier: Operating System :: OS Independent
Classifier: License :: OSI Approved :: GNU General Public License v2 (GPLv2)
Requires-Python: >=2.7,!=3.0.*,!=3.1.*,!=3.2.*,!=3.3.*,!=3.4.*,!=3.5.*
Provides-Extra: test
